{
  "boats": [
    {
      "id": 389843,
      "name": "Beneateau Oceanis 321",
      "price": "35000",
      "oldprice": "36000",
      "type": "sailboat",
      "year": 1995,
      "photoid": "389843",
      "material": "polyester",
      "brand": "beneteau"
    },
    {
      "id": 389799,
      "name": "Antaris Regenboog 18",
      "price": "19900",
      "oldprice": "19000",
      "type": "sportboat",
      "year": 2008,
      "photoid": "389799",
      "material": "wood",
      "brand": "antaris"
    },
    {
      "id": 389789,
      "name": "Babro Classic 12,60",
      "price": "285000",
      "oldprice": "280000",
      "type": "motorboat",
      "year": 2007,
      "photoid": "389789",      
      "material": "aluminium",
      "brand": "barbo"
    },
    {
      "id": 388832,
      "name": "Seabob F5",
      "price": "9923",
      "oldprice": "10000",
      "type": "scooter",
      "year": 2011,
      "photoid": "388832",
      "material": "polyester",
      "brand": "seabob"
    },
    {
      "id": 389808,
      "name": "LM 27",
      "price": "11500",
      "oldprice": "12000",
      "type": "sailboat",
      "year": 1980,
      "photoid": "389808",
      "material": "steel",
      "brand": "admiral"
    }
  ]
}
